setup.py
django_tdd/__init__.py
django_tdd/tests.py
django_tdd.egg-info/PKG-INFO
django_tdd.egg-info/SOURCES.txt
django_tdd.egg-info/dependency_links.txt
django_tdd.egg-info/top_level.txt
django_tdd/management/__init__.py
django_tdd/management/commands/__init__.py
django_tdd/management/commands/tdd.py