Metadata-Version: 1.1
Name: django-tdd
Version: 0.1.0
Summary: A continuous test runner for Django
Home-page: https://github.com/kcharvey/django-tdd
Author: Kevin Harvey
Author-email: kcharvey@gmail.com
License: Public Domain
Platform: UNKNOWN
Classifier: Programming Language :: Python
Classifier: Development Status :: 3 - Alpha
Classifier: Intended Audience :: Developers
Classifier: License :: Public Domain
Classifier: Framework :: Django
Classifier: Operating System :: OS Independent
